<?xml version="1.0" encoding="utf-8"?>
<deployment>
  <id>efebb27ac3cd47b594ad4ef13233c6ed</id>
  <author>N/A</author>
  <deployer>OneDeploy</deployer>
  <authorEmail>N/A</authorEmail>
  <message>OneDeploy</message>
  <progress></progress>
  <status>Success</status>
  <statusText></statusText>
  <lastSuccessEndTime>2026-05-24T06:07:15.6476574Z</lastSuccessEndTime>
  <receivedTime>2026-05-24T06:07:01.7411571Z</receivedTime>
  <startTime>2026-05-24T06:07:02.259141Z</startTime>
  <endTime>2026-05-24T06:07:15.6476574Z</endTime>
  <complete>True</complete>
  <is_temp>False</is_temp>
  <is_readonly>True</is_readonly>
  <project_type>BASIC</project_type>
  <vsproject_id></vsproject_id>
</deployment>